chrome_spider/__init__.py
chrome_spider/__main__.py
chrome_spider/app.py
chrome_spider/common/__init__.py
chrome_spider/common/config.py
chrome_spider/common/log.py
chrome_spider/common/sql.py
chrome_spider/spider/__init__.py
chrome_spider/spider/cookie.py
chrome_spider/spider/main.py
chrome_spider-0.0.4.dist-info/LICENSE
chrome_spider-0.0.4.dist-info/METADATA
chrome_spider-0.0.4.dist-info/WHEEL
chrome_spider-0.0.4.dist-info/entry_points.txt
chrome_spider-0.0.4.dist-info/top_level.txt
chrome_spider-0.0.4.dist-info/RECORD
