Metadata-Version: 2.1
Name: chrome-spider
Version: 0.0.4
Home-page: https://github.com/gaianote/chrome-spider
Author: gaianote
Author-email: gaianote311@gmail.com
Classifier: Programming Language :: Python :: 3 :: Only
Classifier: Programming Language :: Python :: 3.6
Classifier: Programming Language :: Python :: 3.7
Classifier: Programming Language :: Python :: 3.8
Classifier: License :: OSI Approved :: MIT License
Classifier: Operating System :: MacOS
License-File: LICENSE
Requires-Dist: webdriver-manager (>=3.8.3)
Requires-Dist: selenium (>=4.4.3)
Provides-Extra: dev
